utempid/__init__.py
utempid/utempid.py
utempid-1.0.0.dist-info/LICENSE
utempid-1.0.0.dist-info/METADATA
utempid-1.0.0.dist-info/WHEEL
utempid-1.0.0.dist-info/top_level.txt
utempid-1.0.0.dist-info/RECORD
