Metadata-Version: 2.1
Name: utempid
Version: 1.0.0
Summary: Unique temporary id generator for python
Home-page: https://github.com/mschoema/utempid
Author: Maxime Schoemans
Author-email: maxime.schoemans@ulb.ac.be
License: UNKNOWN
Platform: UNKNOWN
Classifier: Programming Language :: Python :: 3.7
Classifier: License :: OSI Approved :: MIT License
Classifier: Operating System :: OS Independent
Requires-Python: >=3.7
